{
  "sorted_middleware": [],
  "middleware": {
    "/": {
      "files": [
        "server/edge/chunks/_9dd07395._.js",
        "server/edge/chunks/[root-of-the-server]__de110ef0._.js",
        "server/edge/chunks/edge-wrapper_24e2925a.js"
      ],
      "name": "middleware",
      "page": "/",
      "matchers": [
        {
          "regexp": "/:nextData(_next/data/[^/]{1,})?/profile/:path*{(\\\\.json)}?",
          "originalSource": "/profile/:path*"
        },
        {
          "regexp": "/:nextData(_next/data/[^/]{1,})?/workouts/:path*{(\\\\.json)}?",
          "originalSource": "/workouts/:path*"
        },
        {
          "regexp": "/:nextData(_next/data/[^/]{1,})?/routines/:path*{(\\\\.json)}?",
          "originalSource": "/routines/:path*"
        },
        {
          "regexp": "/:nextData(_next/data/[^/]{1,})?/protected/:path*{(\\\\.json)}?",
          "originalSource": "/protected/:path*"
        },
        {
          "regexp": "/:nextData(_next/data/[^/]{1,})?/sign-in{(\\\\.json)}?",
          "originalSource": "/sign-in"
        },
        {
          "regexp": "/:nextData(_next/data/[^/]{1,})?/sign-up{(\\\\.json)}?",
          "originalSource": "/sign-up"
        },
        {
          "regexp": "/:nextData(_next/data/[^/]{1,})?/forgot-password{(\\\\.json)}?",
          "originalSource": "/forgot-password"
        }
      ],
      "wasm": [],
      "assets": [],
      "env": {
        "__NEXT_BUILD_ID": "development",
        "NEXT_SERVER_ACTIONS_ENCRYPTION_KEY": "WzN9ZXX9CU+D2KFP7na2jZH9bHdVHBgiXwMsjC7tknc=",
        "__NEXT_PREVIEW_MODE_ID": "477f6131ab2be9872c3df9f7e0d87141",
        "__NEXT_PREVIEW_MODE_ENCRYPTION_KEY": "253e90cee941c2b503c280db25f4cd097050d2a4c9ca5eabfdde89734542784c",
        "__NEXT_PREVIEW_MODE_SIGNING_KEY": "295694e3f8f7945c9c973c51767057b541b13b4f38cd94c196c09ca2c669b29c"
      }
    }
  },
  "instrumentation": null,
  "functions": {}
}